yahel/CHANGELOG.md
yahel/LICENSE
yahel/README.md
yahel/__init__.py
yahel/_init_.py
yahel/graficos/__init__.py
yahel/graficos/__pycache__/__init__.cpython-312.pyc
yahel/graficos/__pycache__/bar_plot.cpython-312.pyc
yahel/graficos/__pycache__/histogram_plot.cpython-312.pyc
yahel/graficos/__pycache__/line_plot.cpython-312.pyc
yahel/graficos/__pycache__/pie_plot.cpython-312.pyc
yahel/graficos/bar_plot.py
yahel/graficos/histogram_plot.py
yahel/graficos/line_plot.py
yahel/graficos/pie_plot.py
yahel/visuals/__init__.py
yahel-0.1.3.dist-info/METADATA
yahel-0.1.3.dist-info/WHEEL
yahel-0.1.3.dist-info/RECORD
